{
  "company_name": "google",
  "stock_code": "GOOG",
  "newsdesc": "Google is implementing a new 'risk-based' approach to Android security updates. This strategy focuses on addressing the most critical security vulnerabilities first. The change aims to improve overall Android security by prioritizing high-risk issues.;The iPhone 17 has improved its base storage. The article suggests that Samsung and Google should adopt a similar approach. This change is viewed as a positive step in the right direction.;Rumors suggest Google's AI Mode may soon become the default search tool, replacing the classic Google Search. This shift reflects the growing importance of AI in search technology. Experts predict AI mode will eventually replace the traditional list of links for search results.;DeepMind CEO Demis Hassabis believes the ability to learn will be the most crucial skill in the future. He emphasizes this due to AI's increasing impact on education, careers, and daily routines. Individuals who can adapt and acquire new knowledge effectively will thrive in an AI-driven world.;Google is deploying its TPUs in smaller cloud providers' data centers, challenging Nvidia's dominance. This strategic move signifies a broader competition in the AI infrastructure market. The deployment goes beyond a simple product launch, indicating a calculated long-term strategy.",
  "sentiment": "Positive",
  "people_names": [
    "Demis Hassabis"
  ],
  "places_names": [],
  "other_companies_referred": [
    "Samsung",
    "Nvidia",
    "DeepMind"
  ],
  "related_industries": [
    "Technology",
    "AI",
    "Security",
    "Cloud Computing",
    "Semiconductors"
  ],
  "market_implications": "Google's moves in Android security, AI search, and cloud infrastructure signal a positive outlook, potentially increasing investor confidence. Competition with Nvidia in AI infrastructure could impact both companies' market share.",
  "confidence_score": 0.95
}
